sigmatch/__init__.py
sigmatch/errors.py
sigmatch/matcher.py
sigmatch/py.typed
sigmatch-0.0.4.dist-info/LICENSE
sigmatch-0.0.4.dist-info/METADATA
sigmatch-0.0.4.dist-info/WHEEL
sigmatch-0.0.4.dist-info/top_level.txt
sigmatch-0.0.4.dist-info/RECORD
